ReverseTwitterScraper/Scraper.py
ReverseTwitterScraper/__init__.py
ReverseTwitterScraper-0.8.dist-info/LICENSE
ReverseTwitterScraper-0.8.dist-info/METADATA
ReverseTwitterScraper-0.8.dist-info/WHEEL
ReverseTwitterScraper-0.8.dist-info/top_level.txt
ReverseTwitterScraper-0.8.dist-info/RECORD
