Metadata-Version: 2.1
Name: ReverseTwitterScraper
Version: 0.8
Summary: A Python package for scraping Twitter data without API. With proxy and account-cookie support
Home-page: https://github.com/1220moritz/reverse-twitter-scraper
Author: 1220moritz
Project-URL: Documentation, https://github.com/1220moritz/reverse-twitter-scraper/blob/main/README.md
Project-URL: Github, https://github.com/1220moritz/reverse-twitter-scraper
Project-URL: PyPi, https://pypi.org/project/ReverseTwitterScraper/
Project-URL: Contact, https://discordapp.com/users/713118695165263923
Classifier: Programming Language :: Python :: 3
Classifier: License :: OSI Approved :: MIT License
Classifier: Operating System :: OS Independent
Requires-Python: >=3.6
License-File: LICENSE
Requires-Dist: selenium-wire
Requires-Dist: selenium
Requires-Dist: httpx
Requires-Dist: asyncio
